CUDAAAAGH/__init__.py
cudaaaagh-0.1.4.dist-info/METADATA
cudaaaagh-0.1.4.dist-info/WHEEL
cudaaaagh-0.1.4.dist-info/RECORD
